pipeline_gazprom_infotech/__init__.py
pipeline_gazprom_infotech/ipl.py
pipeline_gazprom_infotech/tpo.py
pipeline_gazprom_infotech/codes/__init__.py
pipeline_gazprom_infotech/codes/company.py
pipeline_gazprom_infotech/codes/feature.py
pipeline_gazprom_infotech/codes/kbd.py
pipeline_gazprom_infotech/codes/passtype.py
pipeline_gazprom_infotech/codes/pigtype.py
pipeline_gazprom_infotech/codes/pypeline.py
pipeline_gazprom_infotech/codes/tube.py
pipeline_gazprom_infotech-1.3.dist-info/LICENSE
pipeline_gazprom_infotech-1.3.dist-info/METADATA
pipeline_gazprom_infotech-1.3.dist-info/WHEEL
pipeline_gazprom_infotech-1.3.dist-info/top_level.txt
pipeline_gazprom_infotech-1.3.dist-info/RECORD
