Metadata-Version: 2.1
Name: pipeline-gazprom-infotech
Version: 1.3
Summary: Library for making infotech.xml files.
Home-page: https://github.com/vb64/pipeline.gazprom.infotech
Author: Vitaly Bogomolov
Author-email: mail@vitaly-bogomolov.ru
License: UNKNOWN
Project-URL: Bug Tracker, https://github.com/vb64/pipeline.gazprom.infotech/issues
Platform: UNKNOWN
Classifier: Programming Language :: Python :: 3
Classifier: License :: OSI Approved :: MIT License
Classifier: Operating System :: OS Independent
Requires-Python: >=3.6
Requires-Dist: lxml==5.3.0
